evalseg/__init__.py
evalseg/__main__.py
evalseg/base.py
evalseg/cli/__init__.py
evalseg/cli/multi_runner.py
evalseg/common/__init__.py
evalseg/common/cache.py
evalseg/common/custom_lists.py
evalseg/common/dict_op.py
evalseg/common/numpy_encoder.py
evalseg/common/object.py
evalseg/common/parallel.py
evalseg/common/tests/__init__.py
evalseg/common/tests/test_parallel.py
evalseg/compress/__init__.py
evalseg/compress/sparse.py
evalseg/compress/voxel.py
evalseg/ct_helper/__init__.py
evalseg/ct_helper/clahe.py
evalseg/ct_helper/roi.py
evalseg/geometry/__init__.py
evalseg/geometry/boundary.py
evalseg/geometry/connected_components.py
evalseg/geometry/distance.py
evalseg/geometry/hole.py
evalseg/geometry/region_finder.py
evalseg/geometry/roi.py
evalseg/geometry/skeleton.py
evalseg/geometry/slice.py
evalseg/geometry/tests/__init__.py
evalseg/io/__init__.py
evalseg/io/dataset.py
evalseg/io/nib.py
evalseg/io/nib_dataset.py
evalseg/io/segment_array.py
evalseg/metrics/__init__.py
evalseg/metrics/abstract_metric.py
evalseg/metrics/boundary_distance.py
evalseg/metrics/hd.py
evalseg/metrics/hd_todo.py
evalseg/metrics/metric_constants.py
evalseg/metrics/mme.py
evalseg/metrics/multi_class_metric copy.py
evalseg/metrics/multi_class_metric.py
evalseg/metrics/multi_metric.py
evalseg/metrics/normalized_surface_dis.py
evalseg/metrics/traditional.py
evalseg/metrics/volume_similarity.py
evalseg/metrics/voxel.py
evalseg/metrics/aggregator/__init__.py
evalseg/metrics/aggregator/aggregator_abs.py
evalseg/metrics/aggregator/average.py
evalseg/metrics/aggregator/cm_calculators.py
evalseg/metrics/aggregator/collect.py
evalseg/metrics/aggregator/rank_aggregator.py
evalseg/metrics/aggregator/to_df.py
evalseg/ui/__init__.py
evalseg/ui/dataset_viewer.py
evalseg/ui/img_tools.py
evalseg/ui/multi_plot_2d.py
evalseg/ui/multi_plot_3d.py
evalseg/ui/myplt.py
evalseg/ui/ortho_slicer.py
evalseg/ui/plot_metric.py
evalseg/ui/spider_chart.py
evalseg/ui3d/__init__.py
evalseg/ui3d/k3d_subplots.py
evalseg-2.7.dist-info/LICENSE
evalseg-2.7.dist-info/METADATA
evalseg-2.7.dist-info/WHEEL
evalseg-2.7.dist-info/entry_points.txt
evalseg-2.7.dist-info/top_level.txt
evalseg-2.7.dist-info/RECORD
