Metadata-Version: 2.1
Name: evalseg
Version: 2.7
Summary: Medical Image Segmentation Evaluation
Home-page: https://github.com/modaresimr/evalseg/
Author: modaresimr
License-File: LICENSE
Requires-Dist: pandas (>=0.23.3)
Requires-Dist: numpy (>=1.14.5)
Requires-Dist: matplotlib (>=2.2.0)
Requires-Dist: nibabel
Requires-Dist: tqdm
Requires-Dist: ipywidgets
Requires-Dist: diskcache
Requires-Dist: compress-pickle
Requires-Dist: opencv-python
Requires-Dist: scipy
Requires-Dist: edt
Requires-Dist: scikit-image
Requires-Dist: connected-components-3d
Requires-Dist: sparse
Requires-Dist: k3d
Requires-Dist: ipython
Requires-Dist: typing-extensions
Requires-Dist: psutil
Requires-Dist: auto-profiler
Provides-Extra: test
Requires-Dist: pytest ; extra == 'test'
Requires-Dist: coverage ; extra == 'test'
Requires-Dist: flake8 ; extra == 'test'
Requires-Dist: black ; extra == 'test'
Requires-Dist: isort ; extra == 'test'
Requires-Dist: pytest-cov ; extra == 'test'
Requires-Dist: codecov ; extra == 'test'
Requires-Dist: mypy ; extra == 'test'
Requires-Dist: gitchangelog ; extra == 'test'
Requires-Dist: mkdocs ; extra == 'test'
